semcache/__init__.py
semcache/client.py
semcache/exceptions.py
semcache/py.typed
semcache-0.1.0.dist-info/licenses/LICENSE
semcache-0.1.0.dist-info/METADATA
semcache-0.1.0.dist-info/WHEEL
semcache-0.1.0.dist-info/top_level.txt
semcache-0.1.0.dist-info/RECORD
