Metadata-Version: 2.4
Name: semcache
Version: 0.1.0
Summary: A Python library for the Semcache API
Author-email: Louis Cameron Booth <contact@semcache.io>, Jacob Hedén Malm <contact@semcache.io>
License: MIT
Project-URL: Homepage, https://github.com/sensoris/semcache-python
Project-URL: Bug Tracker, https://github.com/sensoris/semcache-python/issues
Project-URL: Documentation, https://github.com/sensoris/semcache-python#readme
Project-URL: Source Code, https://github.com/sensoris/semcache-python
Keywords: cache,semantic,caching,semcache,api,client
Classifier: Development Status :: 3 - Alpha
Classifier: Intended Audience :: Developers
Classifier: License :: OSI Approved :: MIT License
Classifier: Operating System :: OS Independent
Classifier: Programming Language :: Python :: 3
Classifier: Programming Language :: Python :: 3.8
Classifier: Programming Language :: Python :: 3.9
Classifier: Programming Language :: Python :: 3.10
Classifier: Programming Language :: Python :: 3.11
Classifier: Programming Language :: Python :: 3.12
Classifier: Topic :: Software Development :: Libraries :: Python Modules
Classifier: Topic :: Internet :: WWW/HTTP
Requires-Python: >=3.8
License-File: LICENSE
Requires-Dist: requests>=2.28.0
Provides-Extra: dev
Requires-Dist: pytest>=7.0.0; extra == "dev"
Requires-Dist: pytest-cov>=4.0.0; extra == "dev"
Requires-Dist: black>=23.0.0; extra == "dev"
Requires-Dist: mypy>=1.0.0; extra == "dev"
Requires-Dist: types-requests>=2.28.0; extra == "dev"
Requires-Dist: build>=0.10.0; extra == "dev"
Requires-Dist: twine>=4.0.0; extra == "dev"
Dynamic: license-file
